{"totalResultsCount":18,"geonames":[{"countryName":"Hong Kong","adminCode1":"HCW","fclName":"country, state, region,...","countryCode":"HK","lng":114.144859313965,"fcodeName":"first-order administrative division","toponymName":"Central and Western District","fcl":"A","name":"Central and Western District","fcode":"ADM1","geonameId":7533598,"lat":22.2821869181907,"adminName1":"Central and Western","population":250064},{"countryName":"Hong Kong","adminCode1":"HEA","fclName":"country, state, region,...","countryCode":"HK","lng":114.179105758667,"fcodeName":"first-order administrative division","toponymName":"Eastern","fcl":"A","name":"Eastern","fcode":"ADM1","geonameId":7533608,"lat":22.2798836754644,"adminName1":"Eastern","population":587690},{"countryName":"Hong Kong","adminCode1":"NIS","fclName":"country, state, region,...","countryCode":"HK","lng":114.2333333,"fcodeName":"first-order administrative division","toponymName":"Islands District","fcl":"A","name":"Islands District","fcode":"ADM1","geonameId":1819708,"lat":22.35,"adminName1":"Islands","population":137122},{"countryName":"Hong Kong","adminCode1":"KKC","fclName":"country, state, region,...","countryCode":"HK","lng":114.142541885376,"fcodeName":"first-order administrative division","toponymName":"Kowloon City","fcl":"A","name":"Kowloon City","fcode":"ADM1","geonameId":7533612,"lat":22.2864756138935,"adminName1":"Kowloon City","population":362501},{"countryName":"Hong Kong","adminCode1":"NKT","fclName":"country, state, region,...","countryCode":"HK","lng":114.143314361572,"fcodeName":"first-order administrative division","toponymName":"Kwai Tsing","fcl":"A","name":"Kwai Tsing","fcode":"ADM1","geonameId":7533615,"lat":22.2866344519485,"adminName1":"Kwai Tsing","population":523300},{"countryName":"Hong Kong","adminCode1":"KKT","fclName":"country, state, region,...","countryCode":"HK","lng":114.141941070557,"fcodeName":"first-order administrative division","toponymName":"Kwon Tong","fcl":"A","name":"Kwon Tong","fcode":"ADM1","geonameId":7533614,"lat":22.28719038372,"adminName1":"Kwon Tong","population":587423},{"countryName":"Hong Kong","adminCode1":"NNO","fclName":"country, state, region,...","countryCode":"HK","lng":114.17781829834,"fcodeName":"first-order administrative division","toponymName":"North","fcl":"A","name":"North","fcode":"ADM1","geonameId":7533617,"lat":22.3027555755483,"adminName1":"North","population":280730},{"countryName":"Hong Kong","adminCode1":"NSK","fclName":"country, state, region,...","countryCode":"HK","lng":114.270172119141,"fcodeName":"first-order administrative division","toponymName":"Sai Kung District","fcl":"A","name":"Sai Kung District","fcode":"ADM1","geonameId":1819049,"lat":22.3819840734118,"adminName1":"Sai Kung","population":406442},{"countryName":"Hong Kong","adminCode1":"NST","fclName":"country, state, region,...","countryCode":"HK","lng":114.132070541382,"fcodeName":"first-order administrative division","toponymName":"Sha Tin","fcl":"A","name":"Sha Tin","fcode":"ADM1","geonameId":7533618,"lat":22.2831399730491,"adminName1":"Sha Tin","population":607544},{"countryName":"Hong Kong","adminCode1":"KSS","fclName":"country, state, region,...","countryCode":"HK","lng":114.145460128784,"fcodeName":"first-order administrative division","toponymName":"Sham Shui Po","fcl":"A","name":"Sham Shui Po","fcode":"ADM1","geonameId":7533611,"lat":22.2864756138935,"adminName1":"Sham Shui Po","population":365540},{"countryName":"Hong Kong","adminCode1":"HSO","fclName":"country, state, region,...","countryCode":"HK","lng":114.150609970093,"fcodeName":"first-order administrative division","toponymName":"Southern","fcl":"A","name":"Southern","fcode":"ADM1","geonameId":7533609,"lat":22.2819486534611,"adminName1":"Southern","population":275162},{"countryName":"Hong Kong","adminCode1":"NTP","fclName":"country, state, region,...","countryCode":"HK","lng":114.1666667,"fcodeName":"first-order administrative division","toponymName":"Tai Po District","fcl":"A","name":"Tai Po District","fcode":"ADM1","geonameId":1818672,"lat":22.4166667,"adminName1":"Tai Po","population":293542},{"countryName":"Hong Kong","adminCode1":"NTW","fclName":"country, state, region,...","countryCode":"HK","lng":114.0833333,"fcodeName":"first-order administrative division","toponymName":"Tsuen Wan District","fcl":"A","name":"Tsuen Wan District","fcode":"ADM1","geonameId":1818458,"lat":22.35,"adminName1":"Tsuen Wan","population":288728},{"countryName":"Hong Kong","adminCode1":"NTM","fclName":"country, state, region,...","countryCode":"HK","lng":114.138250350952,"fcodeName":"first-order administrative division","toponymName":"Tuen Mun","fcl":"A","name":"Tuen Mun","fcode":"ADM1","geonameId":7533616,"lat":22.2851254831389,"adminName1":"Tuen Mun","population":502035},{"countryName":"Hong Kong","adminCode1":"HWC","fclName":"country, state, region,...","countryCode":"HK","lng":114.161596298218,"fcodeName":"first-order administrative division","toponymName":"Wan Chai","fcl":"A","name":"Wan Chai","fcode":"ADM1","geonameId":7533607,"lat":22.2828222888181,"adminName1":"Wan Chai","population":155196},{"countryName":"Hong Kong","adminCode1":"KWT","fclName":"country, state, region,...","countryCode":"HK","lng":114.141597747803,"fcodeName":"first-order administrative division","toponymName":"Wong Tai Sin","fcl":"A","name":"Wong Tai Sin","fcode":"ADM1","geonameId":7533613,"lat":22.2874286395167,"adminName1":"Wong Tai Sin","population":423521},{"countryName":"Hong Kong","adminCode1":"KYT","fclName":"country, state, region,...","countryCode":"HK","lng":114.176959991455,"fcodeName":"first-order administrative division","toponymName":"Yau Tsim Mong","fcl":"A","name":"Yau Tsim Mong","fcode":"ADM1","geonameId":7533610,"lat":22.2809161682745,"adminName1":"Yau Tsim Mong","population":280548},{"countryName":"Hong Kong","adminCode1":"NYL","fclName":"country, state, region,...","countryCode":"HK","lng":114.05,"fcodeName":"first-order administrative division","toponymName":"Yuen Long District","fcl":"A","name":"Yuen Long District","fcode":"ADM1","geonameId":1818224,"lat":22.4166667,"adminName1":"Yuen Long","population":534192}]}