{"totalResultsCount":11,"geonames":[{"countryName":"Barbados","adminCode1":"01","fclName":"country, state, region,...","countryCode":"BB","lng":-59.5333333,"fcodeName":"first-order administrative division","toponymName":"Christ Church","fcl":"A","name":"Christ Church","fcode":"ADM1","geonameId":3373988,"lat":13.0833333,"adminName1":"Christ Church","population":48119},{"countryName":"Barbados","adminCode1":"02","fclName":"country, state, region,...","countryCode":"BB","lng":-59.5666667,"fcodeName":"first-order administrative division","toponymName":"Saint Andrew","fcl":"A","name":"Saint Andrew","fcode":"ADM1","geonameId":3373580,"lat":13.2333333,"adminName1":"Saint Andrew","population":6436},{"countryName":"Barbados","adminCode1":"03","fclName":"country, state, region,...","countryCode":"BB","lng":-59.5333333,"fcodeName":"first-order administrative division","toponymName":"Saint George","fcl":"A","name":"Saint George","fcode":"ADM1","geonameId":3373572,"lat":13.1333333,"adminName1":"Saint George","population":18287},{"countryName":"Barbados","adminCode1":"04","fclName":"country, state, region,...","countryCode":"BB","lng":-59.6166667,"fcodeName":"first-order administrative division","toponymName":"Saint James","fcl":"A","name":"Saint James","fcode":"ADM1","geonameId":3373570,"lat":13.2166667,"adminName1":"Saint James","population":21454},{"countryName":"Barbados","adminCode1":"05","fclName":"country, state, region,...","countryCode":"BB","lng":-59.4833333,"fcodeName":"first-order administrative division","toponymName":"Saint John","fcl":"A","name":"Saint John","fcode":"ADM1","geonameId":3373569,"lat":13.1666667,"adminName1":"Saint John","population":10421},{"countryName":"Barbados","adminCode1":"06","fclName":"country, state, region,...","countryCode":"BB","lng":-59.5333333,"fcodeName":"first-order administrative division","toponymName":"Saint Joseph","fcl":"A","name":"Saint Joseph","fcode":"ADM1","geonameId":3373568,"lat":13.2,"adminName1":"Saint Joseph","population":7764},{"countryName":"Barbados","adminCode1":"07","fclName":"country, state, region,...","countryCode":"BB","lng":-59.6166667,"fcodeName":"first-order administrative division","toponymName":"Saint Lucy","fcl":"A","name":"Saint Lucy","fcode":"ADM1","geonameId":3373565,"lat":13.3,"adminName1":"Saint Lucy","population":9706},{"countryName":"Barbados","adminCode1":"08","fclName":"country, state, region,...","countryCode":"BB","lng":-59.6,"fcodeName":"first-order administrative division","toponymName":"Saint Michael","fcl":"A","name":"Saint Michael","fcode":"ADM1","geonameId":3373557,"lat":13.1166667,"adminName1":"Saint Michael","population":99609},{"countryName":"Barbados","adminCode1":"09","fclName":"country, state, region,...","countryCode":"BB","lng":-59.6166667,"fcodeName":"first-order administrative division","toponymName":"Saint Peter","fcl":"A","name":"Saint Peter","fcode":"ADM1","geonameId":3373554,"lat":13.25,"adminName1":"Saint Peter","population":11544},{"countryName":"Barbados","adminCode1":"10","fclName":"country, state, region,...","countryCode":"BB","lng":-59.4666667,"fcodeName":"first-order administrative division","toponymName":"Saint Philip","fcl":"A","name":"Saint Philip","fcode":"ADM1","geonameId":3373553,"lat":13.1166667,"adminName1":"Saint Philip","population":20944},{"countryName":"Barbados","adminCode1":"11","fclName":"country, state, region,...","countryCode":"BB","lng":-59.5833333,"fcodeName":"first-order administrative division","toponymName":"Saint Thomas","fcl":"A","name":"Saint Thomas","fcode":"ADM1","geonameId":3373551,"lat":13.1833333,"adminName1":"Saint Thomas","population":11850}]}